{
    "initial_training_samples": 2706,
    "initial_Train_class_counts": {
        "class_0": 101,
        "class_1": 186,
        "class_2": 99,
        "class_3": 70,
        "class_4": 134,
        "class_5": 198,
        "class_6": 179,
        "class_7": 563,
        "class_8": 310,
        "class_9": 164,
        "class_10": 53,
        "class_11": 96,
        "class_12": 46,
        "class_13": 54,
        "class_14": 363,
        "class_15": 90
    },
    "initial_validation_samples": 24358,
    "initial_Val_class_counts": {
        "class_0": 904,
        "class_1": 1677,
        "class_2": 889,
        "class_3": 627,
        "class_4": 1205,
        "class_5": 1781,
        "class_6": 1610,
        "class_7": 5072,
        "class_8": 2791,
        "class_9": 1475,
        "class_10": 481,
        "class_11": 868,
        "class_12": 412,
        "class_13": 481,
        "class_14": 3271,
        "class_15": 814
    },
    "Test_samples": 27065,
    "class_Test_counts": {
        "class_0": 1004,
        "class_1": 1863,
        "class_2": 988,
        "class_3": 697,
        "class_4": 1339,
        "class_5": 1980,
        "class_6": 1790,
        "class_7": 5636,
        "class_8": 3102,
        "class_9": 1639,
        "class_10": 534,
        "class_11": 963,
        "class_12": 458,
        "class_13": 535,
        "class_14": 3634,
        "class_15": 903
    },
    "iterations": [
        {
            "iteration": 1,
            "training_samples": 2706,
            "class_train_counts": {
                "class_0": 101,
                "class_1": 186,
                "class_2": 99,
                "class_3": 70,
                "class_4": 134,
                "class_5": 198,
                "class_6": 179,
                "class_7": 563,
                "class_8": 310,
                "class_9": 164,
                "class_10": 53,
                "class_11": 96,
                "class_12": 46,
                "class_13": 54,
                "class_14": 363,
                "class_15": 90
            },
            "validation_samples": 24358,
            "class_Val_counts": {
                "class_0": 904,
                "class_1": 1677,
                "class_2": 889,
                "class_3": 627,
                "class_4": 1205,
                "class_5": 1781,
                "class_6": 1610,
                "class_7": 5072,
                "class_8": 2791,
                "class_9": 1475,
                "class_10": 481,
                "class_11": 868,
                "class_12": 412,
                "class_13": 481,
                "class_14": 3271,
                "class_15": 814
            },
            "Test_samples": 27065,
            "class_Test_counts": {
                "class_0": 1004,
                "class_1": 1863,
                "class_2": 988,
                "class_3": 697,
                "class_4": 1339,
                "class_5": 1980,
                "class_6": 1790,
                "class_7": 5636,
                "class_8": 3102,
                "class_9": 1639,
                "class_10": 534,
                "class_11": 963,
                "class_12": 458,
                "class_13": 535,
                "class_14": 3634,
                "class_15": 903
            }
        },
        {
            "iteration": 2,
            "training_samples": 3193,
            "class_train_counts": {
                "class_0": 123,
                "class_1": 192,
                "class_2": 106,
                "class_3": 72,
                "class_4": 147,
                "class_5": 201,
                "class_6": 182,
                "class_7": 794,
                "class_8": 326,
                "class_9": 175,
                "class_10": 60,
                "class_11": 114,
                "class_12": 47,
                "class_13": 56,
                "class_14": 507,
                "class_15": 91
            },
            "validation_samples": 23871,
            "class_Val_counts": {
                "class_0": 882,
                "class_1": 1671,
                "class_2": 882,
                "class_3": 625,
                "class_4": 1192,
                "class_5": 1778,
                "class_6": 1607,
                "class_7": 4841,
                "class_8": 2775,
                "class_9": 1464,
                "class_10": 474,
                "class_11": 850,
                "class_12": 411,
                "class_13": 479,
                "class_14": 3127,
                "class_15": 813
            }
        },
        {
            "iteration": 3,
            "training_samples": 3670,
            "class_train_counts": {
                "class_0": 212,
                "class_1": 199,
                "class_2": 111,
                "class_3": 74,
                "class_4": 169,
                "class_5": 206,
                "class_6": 186,
                "class_7": 861,
                "class_8": 336,
                "class_9": 188,
                "class_10": 65,
                "class_11": 116,
                "class_12": 48,
                "class_13": 56,
                "class_14": 751,
                "class_15": 92
            },
            "validation_samples": 23394,
            "class_Val_counts": {
                "class_0": 793,
                "class_1": 1664,
                "class_2": 877,
                "class_3": 623,
                "class_4": 1170,
                "class_5": 1773,
                "class_6": 1603,
                "class_7": 4774,
                "class_8": 2765,
                "class_9": 1451,
                "class_10": 469,
                "class_11": 848,
                "class_12": 410,
                "class_13": 479,
                "class_14": 2883,
                "class_15": 812
            }
        },
        {
            "iteration": 4,
            "training_samples": 4137,
            "class_train_counts": {
                "class_0": 218,
                "class_1": 201,
                "class_2": 116,
                "class_3": 79,
                "class_4": 171,
                "class_5": 210,
                "class_6": 191,
                "class_7": 1222,
                "class_8": 347,
                "class_9": 207,
                "class_10": 72,
                "class_11": 118,
                "class_12": 49,
                "class_13": 57,
                "class_14": 784,
                "class_15": 95
            },
            "validation_samples": 22927,
            "class_Val_counts": {
                "class_0": 787,
                "class_1": 1662,
                "class_2": 872,
                "class_3": 618,
                "class_4": 1168,
                "class_5": 1769,
                "class_6": 1598,
                "class_7": 4413,
                "class_8": 2754,
                "class_9": 1432,
                "class_10": 462,
                "class_11": 846,
                "class_12": 409,
                "class_13": 478,
                "class_14": 2850,
                "class_15": 809
            }
        },
        {
            "iteration": 5,
            "training_samples": 4595,
            "class_train_counts": {
                "class_0": 221,
                "class_1": 282,
                "class_2": 121,
                "class_3": 80,
                "class_4": 174,
                "class_5": 215,
                "class_6": 254,
                "class_7": 1317,
                "class_8": 357,
                "class_9": 211,
                "class_10": 74,
                "class_11": 127,
                "class_12": 51,
                "class_13": 59,
                "class_14": 954,
                "class_15": 98
            },
            "validation_samples": 22469,
            "class_Val_counts": {
                "class_0": 784,
                "class_1": 1581,
                "class_2": 867,
                "class_3": 617,
                "class_4": 1165,
                "class_5": 1764,
                "class_6": 1535,
                "class_7": 4318,
                "class_8": 2744,
                "class_9": 1428,
                "class_10": 460,
                "class_11": 837,
                "class_12": 407,
                "class_13": 476,
                "class_14": 2680,
                "class_15": 806
            }
        },
        {
            "iteration": 6,
            "training_samples": 5044,
            "class_train_counts": {
                "class_0": 222,
                "class_1": 285,
                "class_2": 125,
                "class_3": 82,
                "class_4": 191,
                "class_5": 220,
                "class_6": 262,
                "class_7": 1496,
                "class_8": 367,
                "class_9": 230,
                "class_10": 82,
                "class_11": 133,
                "class_12": 53,
                "class_13": 64,
                "class_14": 1128,
                "class_15": 104
            },
            "validation_samples": 22020,
            "class_Val_counts": {
                "class_0": 783,
                "class_1": 1578,
                "class_2": 863,
                "class_3": 615,
                "class_4": 1148,
                "class_5": 1759,
                "class_6": 1527,
                "class_7": 4139,
                "class_8": 2734,
                "class_9": 1409,
                "class_10": 452,
                "class_11": 831,
                "class_12": 405,
                "class_13": 471,
                "class_14": 2506,
                "class_15": 800
            }
        }
    ]
}